LICENSE
MANIFEST.in
README.rst
asyncio_monkey.py
setup.py
asyncio_monkey.egg-info/PKG-INFO
asyncio_monkey.egg-info/SOURCES.txt
asyncio_monkey.egg-info/dependency_links.txt
asyncio_monkey.egg-info/not-zip-safe
asyncio_monkey.egg-info/requires.txt
asyncio_monkey.egg-info/top_level.txt