Metadata-Version: 1.1
Name: asyncio-monkey
Version: 0.1.1
Summary: monkey patch asyncio modules for expected behaviour
Home-page: https://github.com/wikibusiness/asyncio_monkey
Author: wikibusiness
Author-email: osf@wikibusiness.org
License: UNKNOWN
Keywords: asyncio,monkey patch
Platform: UNKNOWN
Classifier: Development Status :: 4 - Beta
Classifier: Intended Audience :: Developers
Classifier: License :: OSI Approved :: MIT License
Classifier: Programming Language :: Python
Classifier: Programming Language :: Python :: 3
Classifier: Programming Language :: Python :: 3.3
Classifier: Programming Language :: Python :: 3.4
Classifier: Programming Language :: Python :: 3.5
Classifier: Programming Language :: Python :: 3.6
